bigtrill/__init__.py
bigtrill/apps.py
bigtrill/start.py
bigtrill/management/__init__.py
bigtrill/management/commands/__init__.py
bigtrill/management/commands/trillcopy.py
django_bigtrill-2.0.2.dist-info/licenses/LICENSE
django_bigtrill-2.0.2.dist-info/METADATA
django_bigtrill-2.0.2.dist-info/WHEEL
django_bigtrill-2.0.2.dist-info/entry_points.txt
django_bigtrill-2.0.2.dist-info/top_level.txt
django_bigtrill-2.0.2.dist-info/RECORD
