Metadata-Version: 2.4
Name: django-bigtrill
Version: 2.0.2
Summary: A simple Django package that will aid you to switch from using the default Django Auth User model to a custom User model in an existing Django project.
Home-page: https://github.com/alexander-any7/django-bigtrill.git
Author: Alexander Anyaegbunam
Author-email: Alexander Anyaegbunam <alexander.any7@gmail.com>
License-Expression: MIT
Project-URL: Homepage, https://github.com/alexander-any7/django-bigtrill.git
Keywords: django,auth,custom user,migration,bigtrill,bigtrill migration,default user model,custom user model,django custom user model,django auth user model,django user model migration,existing project,django existing project
Classifier: Programming Language :: Python :: 3
Classifier: Operating System :: OS Independent
Classifier: Framework :: Django
Requires-Python: >=3
License-File: LICENSE
Requires-Dist: Django>=3.2
Dynamic: license-file
